generic_api_client/__init__.py
generic_api_client/api_connector_interface.py
generic_api_client/api_segments.py
generic_api_client/client_interface.py
generic_api_client/models/__init__.py
generic_api_client/models/api.py
generic_api_client/models/authentication.py
generic_api_client/models/cache.py
generic_api_client/models/model_tree.py
generic_api_client/models/request_template.py
generic_api_client/models/requests.py
generic_api_client/models/target.py
generic_api_client/services/__init__.py
generic_api_client/services/cache_service.py
generic_api_client/services/template_service.py
generic_api_client/utils.py
generic_api_client-0.0.1.dist-info/METADATA
generic_api_client-0.0.1.dist-info/WHEEL
generic_api_client-0.0.1.dist-info/licenses/LICENSE
generic_api_client-0.0.1.dist-info/RECORD
