Metadata-Version: 2.4
Name: generic-api-client
Version: 0.0.1
Summary: Interact with APIs through methods and pydantic models
License-File: LICENSE
Keywords: open,api,client,generic,rest
Author: Alexi Desvignes Nouvel
Requires-Python: >=3.10
Classifier: Programming Language :: Python :: 3
Classifier: Programming Language :: Python :: 3.10
Classifier: Programming Language :: Python :: 3.11
Classifier: Programming Language :: Python :: 3.12
Classifier: Programming Language :: Python :: 3.13
Classifier: Programming Language :: Python :: 3.14
Requires-Dist: docker (>=7.1.0,<8.0.0)
Requires-Dist: jinja2 (>=3.1.6,<4.0.0)
Requires-Dist: pydantic (>=2.11.4,<3.0.0)
Requires-Dist: redis (>=7.1.0,<8.0.0)
Requires-Dist: requests (>=2.32.5,<3.0.0)
Requires-Dist: semver (>=3.0.4,<4.0.0)
Requires-Dist: treelib (>=1.8.0,<2.0.0)
Requires-Dist: urllib3 (>=2.6.3,<3.0.0)
